nbd_colab/__init__.py
nbd_colab/_nbdev.py
nbd_colab/cltemplate.py
nbd_colab/core.py
nbd_colab/dstemplate.py
nbd_colab/gpu.py
nbd_colab/nbtemplate.py
nbd_colab/troubleshooting.py
nbd_colab/tutorial.py
nbd_colab/utils.py
nbd_colab-0.0.10.dist-info/LICENSE
nbd_colab-0.0.10.dist-info/METADATA
nbd_colab-0.0.10.dist-info/WHEEL
nbd_colab-0.0.10.dist-info/entry_points.txt
nbd_colab-0.0.10.dist-info/top_level.txt
nbd_colab-0.0.10.dist-info/RECORD
