Metadata-Version: 2.1
Name: nbd-colab
Version: 0.0.10
Summary: Wrapper, resources and documentation around fastai nbdev to streamline literate programming in Google Colaboratory.
Home-page: https://github.com/hallmx/nbd_colab
Author: Mathew Hall
Author-email: mathew.hall100@gmail.com
License: Apache Software License 2.0
Keywords: nbdev,fastai,colab
Platform: UNKNOWN
Classifier: Development Status :: 3 - Alpha
Classifier: Intended Audience :: Developers
Classifier: License :: OSI Approved :: Apache Software License
Classifier: Natural Language :: English
Classifier: Programming Language :: Python :: 3.6
Classifier: Programming Language :: Python :: 3.7
Classifier: Programming Language :: Python :: 3.8
Requires-Python: >=3.6
Requires-Dist: nbdev
Requires-Dist: fastcore
